Workbook

Sheet Légende 
B3: titre
B5: donnée a changer suivant l'exploitation
B7: donnée fixes
B9: possibilité de changer les données

Sheet cout de traction d'un tracteur 
A2: cout de traction d'un tracteur vignerons | F2: prix du véhicule | G2: 80000
F3: nombre d'heure par ans | G3: 600
F4: PRIX ad bleu | G4: 0.6
A5: Charge fixe par heure | B5: =(G2/B6)/G3+(B7/G3)+(B8/G3)+(B9/G3) -> 29.997619 | F5: prix pneu arrière | G5: 800
A6: amortissement en années | B6: 7 | F6: prix pneu avant | G6: 250
A7: Assurances par ans | B7: 120 | F7: consommation de gasol par heure en litre | G7: 7
A8: frais financier | B8: =G2*G9 -> 6400 | F8: entretiens par litre consommer en pourcentage | G8: 0.25
A9: amortissement hangar par ans | B9: 50 | F9: interet d'emprumt | G9: 0.08
A10: charge variable | B10: =(B11*G7)+B12+B13+B14+(B15/G3) -> 14.7225
A11: Gasole au litre | B11: 1.35
A12: AD bleu 4 à 6 % du gasole | B12: =G7*0.05*G4 -> 0.21
A13: entretiens (huile, filtre) par heure | B13: =B11*G7*G8 -> 2.3625
A14: cout usure pneu par heure | B14: =(2*G5+2*G6)/3000 -> 0.7
A15: réparation | B15: 1200
A16: Charge main d'œuvre par heure | B16: 20
A18: PRIX utilisation par heure | B18: =B5+B10+B16 -> 64.720119

Sheet cout de traction d'un porteur 
A2: cout de traction d'un porteur vignerons | F2: prix du véhicule | G2: 150000
F3: nombre d'heure par ans | G3: 600
F4: PRIX ad bleu | G4: 0.6
A5: Charge fixe par heure | B5: =(G2/B6)/G3+(B7/G3)+(B8/G3)+(B9/G3) -> 56.914286 | F5: prix pneu arrière | G5: 800
A6: amortissement en années | B6: 7 | F6: prix pneu avant | G6: 500
A7: Assurances par ans | B7: 120 | F7: consommation de gasol par heure en litre | G7: 15
A8: frais financier | B8: =G2*G9 -> 12000 | F8: entretiens par litre consommé en pourcentage | G8: 0.25
A9: amortissement hangar par ans | B9: 600 | F9: interet d'emprumt | G9: 0.08
A10: charge variable | B10: =(B11*G7)+B12+B13+B14+(B15/G3) -> 29.9625
A11: Prix Gasole au litre | B11: 1.35
A12: AD bleu 4 à 6 % du gasole | B12: =G7*0.05*G4 -> 0.45
A13: entretiens (huile, filtre) par heure | B13: =B11*G7*G8 -> 5.0625
A14: cout usure pneu par heure | B14: =(2*G5+2*G6)/3000 -> 0.86666667
A15: réparation | B15: 2000
A16: Charge main d'œuvre par heure | B16: 15.7
A18: PRIX utilisation par heure | B18: =B5+B10+B16 -> 102.57679

Sheet  cout d'utilisation d'une cellu
F2: largeur travailler en mettre | G2: 1.5
F3: vitesse d'avacement en m/h | G3: 5500
A4: débit de chantier ha/H | B4: =(G2*G3*G4)/10000 -> 0.66 | F4: coeff d'éfficacité | G4: 0.8
A5: nombre de hectare travaillé par jour | B5: =(G6-(G7*G5))*B4 -> 4.29 | F5: temps de remplissage en h | G5: 0.75
F6: nombre d'heure par jours | G6: 8
F7: Nmbre de remplissage par jour | G7: 2
A10: Charge fixe par heure | F10: prix de la machine | G10: 150000
A11: Amortissement en années | B11: 7 | F11: nombre d'hectar a travailler | G11: 20
A12: assurance par ans | B12: 120 | F12: Nombre de traitement par ans | G12: 12
A13: Frais financier | B13: =(G10*0.1545119)-(G10/B11) -> 1748.2136 | F13: nombe d'heure de pulvé annuelle | G13: =(G11/B4)*G12 -> 363.63636
A14: amortissement hangar par ans | B14: 600 | F14: nombre de pulvé | G14: =G11/B5 -> 4.6620047
A15: PRIX heure de outil | B15: =((G10/B11)+B12+B13+(B14/B11))/G15 -> 241.05669 | F15: heure par pulvé | G15: =97 -> 97
A19: cout de traitement porteur/cellule a l'heure | B19: =B15+'cout de traction d''un porteur '!B18 -> 343.63348
A20: cout de traitement porteur/cellule a l'hectare | B20: =B19/B4 -> 520.65679

Sheet cout d'utilisation d'un pulvé 
F2: largeur travailler en mettre | G2: 3
F3: vitesse d'avacement en m/h | G3: 6000
A4: débit de chantier ha/H | B4: =(G2*G3*G4)/10000 -> 1.35 | F4: coeff d'éfficacité | G4: 0.75
A5: nombre de hectare travaillé par jour | B5: =(G6-(G7*G5))*B4 -> 10.0575 | F5: temps de remplissage en h | G5: 0.75
F6: nombre d'heure par jours | G6: 8.2
F7: Nmbre de remplissage par jour | G7: 1
A10: Charge fixe par heure | F10: prix de la machine | G10: 60000
A11: Amortissement en années | B11: 7 | F11: nombre d'hectar a travailler | G11: 20
A12: assurance par ans | B12: 120 | F12: Nombre de passage par ans | G12: 12
A13: Frais financier | B13: =(G10*0.1545119)-(G10/B11) -> 699.28543 | F13: nombe d'heure de pulvé annuelle | G13: =(G11/B4)*G12 -> 177.77778
A14: amortissement hangar par ans | B14: 600 | F14: nombre de pulvé | G14: =G11/B5 -> 1.9885657
A15: PRIX heure de machine | B15: =((G10/B11)+B12+B13+(B14/B11))/G15 -> 106.00032 | F15: heure par machine | G15: =G13/G14 -> 89.4
A17: cout d'un traitement par tracteur + pulvé a l'heure | B17: =B15+'cout de traction d''un tracteur '!B18 -> 170.72044
A18: cout d'un traitement par tracteur + pulvé a hectare | B18: =B17/B4 -> 126.45958

Sheet disque + Epampreuse 
F2: largeur travailler en mettre | G2: 1.5
F3: vitesse d'avacement en m/h | G3: 3500
A4: débit de chantier ha/H | B4: =(G2*G3*G4)/10000 -> #VALUE! | F4: coeff d'éfficacité
A5: nombre de hectares travaillés | B5: =(G7*G6-(G8*G5))*B4 -> #VALUE! | F5: temps de remplissage en h | G5: 0.25
F6: nombre de jour de travaille | G6: 5
F7: nombre d'heure par jours | G7: 8
F8: Nombre de remplissage par jour | G8: 2
A11: Charge fixe par heure | F11: prix de la machine | G11: 11000
A12: Amortissement en années | B12: 7 | F12: nombre d'hectar a travailler | G12: 20
A13: assurance par ans | B13: 120 | F13: Nombre de utilisation par ans | G13: 1
A14: Frais financier | B14: =(G11*0.1545119)-(G11/B12) -> 128.20233 | F14: nombe d'heure d'utilisation annuelle | G14: =(G12/B4)*G13 -> #VALUE!
A15: amortissement hangar par ans | B15: 600 | F15: nombre de machine | G15: =G12/B5 -> #VALUE!
A16: PRIX a l'heure de l'outil | B16: =((G11/B12)+B13+B14+(B15/B12))/G16 -> #VALUE! | F16: heure par machine | G16: =(G14/G15)*G13 -> #VALUE!
A18: cout d'un utilisation par tracteur + outil a l'heure | B18: =B16+'cout de traction d''un tracteur '!B18 -> #VALUE!
A19: cout d'un utilisation par tracteur + outil a hectare | B19: =B18/B4 -> #VALUE!

Sheet vibroculteur + semoir +herse  
F2: largeur travailler en mettre | G2: 1.5
F3: vitesse d'avacement en m/h | G3: 0
A4: débit de chantier ha/H | B4: =(G2*G3*G4)/10000 -> 0 | F4: coeff d'éfficacité | G4: 0.8
A5: nombre de hectares travaillés | B5: =(G7*G6-(G8*G5))*B4 -> 0 | F5: temps de remplissage en h | G5: 0.25
F6: nombre de jour de travaille | G6: 5
F7: nombre d'heure par jours | G7: 8
F8: Nombre de remplissage par jour | G8: 1
A11: Charge fixe par heure | F11: prix de la machine | G11: 6000
A12: Amortissement en années | B12: 7 | F12: nombre d'hectar a travailler | G12: 5.6
A13: assurance par ans | B13: 120 | F13: Nombre de utilisation par ans | G13: 2
A14: Frais financier | B14: =(G11*0.1545119)-(G11/B12) -> 69.928543 | F14: nombe d'heure d'utilisation annuelle | G14: =(G12/B4)*G13 -> #DIV/0!
A15: amortissement hangar par ans | B15: 600 | F15: nombre de machine | G15: =G12/B5 -> #DIV/0!
A16: PRIX a l'heure de l'outil | B16: =((G11/B12)+B13+B14+(B15/B12))/G14 -> #DIV/0! | F16: heure par machine | G16: =G14/G15*G13 -> #DIV/0!
A18: cout d'un utilisation par tracteur + outil a l'heure | B18: =B16+'cout de traction d''un tracteur '!B18 -> #DIV/0!
A19: cout d'un utilisation par tracteur + outil a hectare | B19: =B18/B4 -> #DIV/0!

Sheet rouleaux faca + epampreuse 
F2: largeur travailler en mettre | G2: 2
F3: vitesse d'avacement en m/h | G3: 3500
A4: débit de chantier ha/H | B4: =(G2*G3*G4)/10000 -> 0.56 | F4: coeff d'éfficacité | G4: 0.8
A5: nombre de hectares travaillés | B5: =(G7*G6-(G8*G5))*B4 -> 31.08 | F5: temps de remplissage en h | G5: 0.25
F6: nombre de jour de travaille | G6: 7
F7: nombre d'heure par jours | G7: 8
F8: Nombre de remplissage par jour | G8: 2
A11: Charge fixe par heure | F11: prix de la machine | G11: 0
A12: Amortissement en années | B12: 7 | F12: nombre d'hectar a travailler | G12: 26
A13: assurance par ans | B13: 120 | F13: Nombre de utilisation par ans | G13: 3
A14: Frais financier | B14: =(G11*0.1545119)-(G11/B12) -> 0 | F14: nombe d'heure d'utilisation annuelle | G14: =(G12/B4)*G13 -> 139.28571
A15: amortissement hangar par ans | B15: 600 | F15: nombre de machine | G15: =G12/B5 -> 0.83655084
A16: PRIX a l'heure de l'outil | B16: =((G11/B12)+B13+B14+(B15/B12))/G16 -> 0.41184041 | F16: heure par machine | G16: =(G14/G15)*G13 -> 499.5
A18: cout d'un utilisation par tracteur + outil a l'heure | B18: =B16+'cout de traction d''un tracteur '!B18 -> 65.131959
A19: cout d'un utilisation par tracteur + outil a hectare | B19: =B18/B4 -> 116.30707

Sheet Feuil2
A2: total heure de travaille
A3: cout total de travaille
